{"_links": {"_self": "https://api.planet.com/data/v1/item-types/PSScene4Band/items/20160217_191217_0c74", "assets": "https://api.planet.com/data/v1/item-types/PSScene4Band/items/20160217_191217_0c74/assets/", "thumbnail": "https://api.planet.com/data/v1/item-types/PSScene4Band/items/20160217_191217_0c74/thumb"}, "_permissions": ["assets.basic_analytic_rpc_nitf:download", "assets.analytic_xml:download", "assets.basic_analytic_dn:download", "assets.basic_analytic_dn_xml_nitf:download", "assets.basic_analytic_dn_nitf:download", "assets.basic_analytic_xml:download", "assets.basic_analytic_nitf:download", "assets.basic_analytic_rpc:download", "assets.analytic_dn:download", "assets.basic_udm:download", "assets.basic_analytic_dn_rpc_nitf:download", "assets.analytic:download", "assets.analytic_dn_xml:download", "assets.basic_analytic_dn_xml:download", "assets.basic_analytic_dn_rpc:download", "assets.basic_analytic_xml_nitf:download", "assets.basic_analytic:download", "assets.udm:download"], "geometry": {"coordinates": [[[-98.79973439692867, 41.53295095888891], [-98.77424460302947, 41.54730719171709], [-98.6376854343666, 41.41098786907305], [-98.66319392567208, 41.39663044764642], [-98.79973439692867, 41.53295095888891]]], "type": "Polygon"}, "id": "20160217_191217_0c74", "properties": {"acquired": "2016-02-17T19:12:17.078166Z", "anomalous_pixels": 0, "cloud_cover": 0.01, "columns": 4526, "epsg_code": 32614, "ground_control": true, "gsd": 2.9, "instrument": "PS2", "item_type": "PSScene4Band", "origin_x": 516705, "origin_y": 4599543, "pixel_resolution": 3, "provider": "planetscope", "published": "2017-04-08T14:34:57Z", "quality_category": "standard", "rows": 5567, "satellite_id": "0c74", "strip_id": "146374", "sun_azimuth": 187, "sun_elevation": 36.3, "updated": "2017-10-05T00:23:20Z", "usable_data": 0, "view_angle": 0.6}, "type": "Feature"}